{
  "issue_id": "M5-006",
  "branch": "chore/M5-006",
  "files_changed": [
    "docs/rewrite-quality-analysis-runbook.md",
    "docs/rewrite-quality-analysis-spec.md"
  ],
  "lint": "pass",
  "typecheck": "pass",
  "tests": "pass",
  "dotnet_tests": "skipped",
  "banned_terms_found": [],
  "summary": "Added the owner runbook for generating, interpreting, and safely storing rewrite-quality analysis reports.",
  "title": "docs: add rewrite quality report owner runbook",
  "next_action": "ready_to_commit"
}
